flake8_simplify/__init__.py
flake8_simplify/constants.py
flake8_simplify/utils.py
flake8_simplify/rules/__init__.py
flake8_simplify/rules/ast_assign.py
flake8_simplify/rules/ast_bool_op.py
flake8_simplify/rules/ast_call.py
flake8_simplify/rules/ast_classdef.py
flake8_simplify/rules/ast_compare.py
flake8_simplify/rules/ast_expr.py
flake8_simplify/rules/ast_for.py
flake8_simplify/rules/ast_if.py
flake8_simplify/rules/ast_ifexp.py
flake8_simplify/rules/ast_subscript.py
flake8_simplify/rules/ast_try.py
flake8_simplify/rules/ast_unary_op.py
flake8_simplify/rules/ast_with.py
flake8_simplify-0.30.0.dist-info/entry_points.txt
flake8_simplify-0.30.0.dist-info/licenses/LICENSE
flake8_simplify-0.30.0.dist-info/WHEEL
flake8_simplify-0.30.0.dist-info/METADATA
flake8_simplify-0.30.0.dist-info/RECORD
