Metadata-Version: 2.4
Name: flake8_simplify
Version: 0.30.0
Summary: flake8 plugin which checks for code that can be simplified
Keywords: flake8
Author-email: Martin Thoma <info@martin-thoma.de>
Maintainer-email: Martin Thoma <info@martin-thoma.de>
Requires-Python: >=3.9.0
Classifier: Development Status :: 4 - Beta
Classifier: Environment :: Console
Classifier: Intended Audience :: Developers
Classifier: License :: OSI Approved :: MIT License
Classifier: Natural Language :: English
Classifier: Operating System :: OS Independent
Classifier: Programming Language :: Python :: 3
Classifier: Programming Language :: Python :: 3 :: Only
Classifier: Programming Language :: Python :: 3.9
Classifier: Programming Language :: Python :: 3.10
Classifier: Programming Language :: Python :: 3.11
Classifier: Programming Language :: Python :: 3.12
Classifier: Programming Language :: Python :: 3.13
Classifier: Topic :: Software Development
Classifier: Framework :: Flake8
License-File: LICENSE
Requires-Dist: flake8>=3.7
Project-URL: Homepage, https://github.com/MartinThoma/flake8-simplify
